paramiko_mock/__init__.py
paramiko_mock/channel_mock.py
paramiko_mock/exceptions.py
paramiko_mock/local_filesystem_mock.py
paramiko_mock/metaclasses.py
paramiko_mock/mocked_env.py
paramiko_mock/py.typed
paramiko_mock/sftp_mock.py
paramiko_mock/ssh_mock.py
paramiko_mock/stderr_mock.py
paramiko_mock-2.0.1.dist-info/METADATA
paramiko_mock-2.0.1.dist-info/WHEEL
paramiko_mock-2.0.1.dist-info/licenses/LICENSE.txt
paramiko_mock-2.0.1.dist-info/RECORD
