Metadata-Version: 2.4
Name: paramiko-mock
Version: 2.0.1
Summary: Mock for paramiko library
Project-URL: Homepage, https://github.com/ghhwer/paramiko-ssh-mock
Project-URL: Repository, https://github.com/ghhwer/paramiko-ssh-mock.git
Project-URL: Issues, https://github.com/ghhwer/paramiko-ssh-mock/issues
Author-email: Caio Cominato <caiopetrellicominato@gmail.com>
License: MIT License
License-File: LICENSE.txt
Classifier: Development Status :: 4 - Beta
Classifier: Intended Audience :: Developers
Classifier: License :: OSI Approved :: MIT License
Classifier: Programming Language :: Python :: 3
Classifier: Programming Language :: Python :: 3.9
Classifier: Programming Language :: Python :: 3.10
Classifier: Programming Language :: Python :: 3.11
Classifier: Programming Language :: Python :: 3.12
Requires-Python: >=3.10
Requires-Dist: paramiko>=3.4.0
Provides-Extra: dev
Requires-Dist: mkdocs-autoapi==0.4.0; extra == 'dev'
Requires-Dist: mkdocs-material==9.6.7; extra == 'dev'
Requires-Dist: mkdocstrings[python]==0.29.0; extra == 'dev'
Requires-Dist: pytest==8.2.0; extra == 'dev'
Provides-Extra: docs
Requires-Dist: mkdocs-autoapi==0.4.0; extra == 'docs'
Requires-Dist: mkdocs-material==9.6.7; extra == 'docs'
Requires-Dist: mkdocstrings[python]==0.29.0; extra == 'docs'
Provides-Extra: test
Requires-Dist: pytest==8.2.0; extra == 'test'
